weakProperty/__init__.py
weakProperty/main.py
weakproperty-0.1.0.dist-info/licenses/LICENSE
weakproperty-0.1.0.dist-info/METADATA
weakproperty-0.1.0.dist-info/WHEEL
weakproperty-0.1.0.dist-info/top_level.txt
weakproperty-0.1.0.dist-info/RECORD
