Metadata-Version: 2.4
Name: weakProperty
Version: 0.1.0
Summary: @property with weakref
Author-email: howShouldIChooseMyUsername <trademark2179@gmail.com>
License: MIT
Keywords: weakref,property
License-File: LICENSE
Dynamic: license-file
